{
  "gitSyncId": "66a9dfd51c79ac7ee4ace222_52d7e360-3260-4556-8235-030178180d71",
  "id": "DISTRICT_UpdateQuery",
  "pluginId": "snowflake-plugin",
  "pluginType": "DB",
  "unpublishedAction": {
    "actionConfiguration": {
      "body": "UPDATE PUBLIC.DISTRICT SET\n\t\tDISTRICT = '{{update_form.fieldState.DISTRICT.isVisible ? update_form.formData.DISTRICT : update_form.sourceData.DISTRICT}}'\nWHERE COVIDCASES = {{data_table.selectedRow.COVIDCASES}};",
      "encodeParamsToggle": true,
      "paginationType": "NONE",
      "pluginSpecifiedTemplates": [
        {
          "value": true
        }
      ],
      "timeoutInMillisecond": 10000
    },
    "confirmBeforeExecute": false,
    "datasource": {
      "id": "basicauth",
      "isAutoGenerated": false,
      "name": "basicauth",
      "pluginId": "snowflake-plugin"
    },
    "executeOnLoad": false,
    "name": "UpdateQuery",
    "pageId": "DISTRICT",
    "userSetOnLoad": false
  }
}