{
  "gitSyncId": "66a9dfd51c79ac7ee4ace222_3e417b46-46cf-4cd0-b56f-5dbab7ba08b0",
  "id": "Page1_adddoc",
  "pluginId": "firestore-plugin",
  "pluginType": "DB",
  "unpublishedAction": {
    "actionConfiguration": {
      "encodeParamsToggle": true,
      "formData": {
        "body": {
          "data": "{\n    \"gender\": \"Female\",\n    \"name\": \"xx New\",\n    \"email\": \"xx@amele.com\"\n  }"
        },
        "command": {
          "data": "ADD_TO_COLLECTION"
        },
        "deleteKeyPath": {
          "data": ""
        },
        "limitDocuments": {
          "data": "10"
        },
        "next": {
          "data": ""
        },
        "orderBy": {
          "data": ""
        },
        "path": {
          "data": "employee"
        },
        "prev": {
          "data": ""
        },
        "smartSubstitution": true,
        "timestampValuePath": {
          "data": ""
        },
        "where": {
          "data": {
            "children": [
              {
                "condition": "EQ"
              }
            ],
            "condition": "AND"
          }
        }
      },
      "paginationType": "NONE",
      "timeoutInMillisecond": 10000
    },
    "confirmBeforeExecute": false,
    "datasource": {
      "id": "fire",
      "isAutoGenerated": false,
      "name": "fire",
      "pluginId": "firestore-plugin"
    },
    "dynamicBindingPathList": [],
    "executeOnLoad": false,
    "name": "adddoc",
    "pageId": "Page1",
    "userSetOnLoad": false
  }
}