{
  "gitSyncId": "66a9dfd51c79ac7ee4ace222_52cece41-e8b2-480f-9103-bcb3e513fc3c",
  "id": "Rw_Api1",
  "pluginId": "google-sheets-plugin",
  "pluginType": "SAAS",
  "unpublishedAction": {
    "actionConfiguration": {
      "encodeParamsToggle": true,
      "formData": {
        "command": {
          "data": "DELETE_ONE"
        },
        "entityType": {
          "data": "SPREADSHEET"
        },
        "pagination": {
          "data": {
            "limit": "20",
            "offset": "0"
          }
        },
        "projection": {
          "data": []
        },
        "queryFormat": {
          "data": "ROWS"
        },
        "range": {
          "data": ""
        },
        "sheetUrl": {
          "data": "https://docs.google.com/spreadsheets/d/1UQ7I6dLFiWdnFAlc9KydFAkfvQITplJiDg6DQZ8zZXc/edit"
        },
        "smartSubstitution": {
          "data": true
        },
        "tableHeaderIndex": {
          "data": "1"
        },
        "where": {
          "data": {
            "condition": "AND"
          }
        }
      },
      "paginationType": "NONE",
      "timeoutInMillisecond": 10000
    },
    "confirmBeforeExecute": false,
    "datasource": {
      "id": "r/w",
      "isAutoGenerated": false,
      "name": "r/w",
      "pluginId": "google-sheets-plugin"
    },
    "dynamicBindingPathList": [],
    "executeOnLoad": false,
    "name": "Api1",
    "pageId": "Rw",
    "userSetOnLoad": false
  }
}